README.md
setup.py
smarsy/__init__.py
smarsy/enums.py
smarsy/parse.py
smarsy.egg-info/PKG-INFO
smarsy.egg-info/SOURCES.txt
smarsy.egg-info/dependency_links.txt
smarsy.egg-info/top_level.txt
tests/__init__.py
tests/test_parser.py
tests/test_person.py
tests/test_requests.py