Metadata-Version: 2.1
Name: smarsy
Version: 0.1.1
Summary: Python REST API wrapper for smarsy.ua website
Home-page: https://github.com/dkultasev/smarsy-py
Author: KulZu
Author-email: dkultasev@gmail.com
License: UNKNOWN
Platform: UNKNOWN
Classifier: Programming Language :: Python :: 3
Classifier: License :: OSI Approved :: MIT License
Classifier: Operating System :: OS Independent
Classifier: Development Status :: 3 - Alpha
Classifier: Intended Audience :: Developers
Requires-Python: >=3.6
